pyspmp/__init__.py
pyspmp/buscar_dados_pi.py
pyspmp/carregar_csv.py
pyspmp/dataset/dataset.csv
pyspmp/dataset.py
pyspmp/parametros/parametros.csv
pyspmp/parametros/parametros_pi.csv
pyspmp/periodos.py
pyspmp/variaveis_out.py
pyspmp-0.1.12.dist-info/METADATA
pyspmp-0.1.12.dist-info/WHEEL
pyspmp-0.1.12.dist-info/RECORD
