Metadata-Version: 2.1
Name: pyspmp
Version: 0.1.12
Summary: Busca e pré seleção de períodos para modelos de monitoramento e predição de máquinas e equipamentos
Author: Leandro Ribeiro de Castro
Author-email: lr.castro@yahoo.com.br
Requires-Python: >=3.8.1,<4.0.0
Classifier: Programming Language :: Python :: 3
Classifier: Programming Language :: Python :: 3.9
Classifier: Programming Language :: Python :: 3.10
Classifier: Programming Language :: Python :: 3.11
Provides-Extra: buscapi
Requires-Dist: pandas (>=1.4.3,<2.0.0)
Requires-Dist: pythonnet (>=3.0.1,<4.0.0) ; extra == "buscapi"
